Metadata-Version: 2.1
Name: iapws
Version: 1.5.4
Summary: Python implementation of standards from The InternationalAssociation for the Properties of Water and Steam
Home-page: https://github.com/jjgomera/iapws
Download-URL: https://github.com/jjgomera/iapws/tarball/v1.5.4
Author: jjgomera
Author-email: jjgomera@gmail.com
License: gpl v3
Classifier: Development Status :: 5 - Production/Stable
Classifier: Intended Audience :: Education
Classifier: Intended Audience :: Science/Research
Classifier: License :: OSI Approved :: GNU General Public License v3 (GPLv3)
Classifier: Natural Language :: English
Classifier: Operating System :: OS Independent
Classifier: Programming Language :: Python
Classifier: Topic :: Scientific/Engineering
Classifier: Topic :: Scientific/Engineering :: Chemistry
Classifier: Topic :: Scientific/Engineering :: Physics
Classifier: Topic :: Software Development :: Libraries :: Python Modules
Requires-Python: >=2.7,!=3.0.*,!=3.1.*,!=3.2.*,!=3.3.*
License-File: LICENSE
